{
    "room": {
        "dimensions": [
            5.45,
            7.87,
            3.54
        ],
        "absorption": 0.2
    },
    "microphone_array": {
        "mic_center": [
            2.95,
            4.37,
            1.5
        ],
        "mic_radius": 0.1,
        "mic_count": 4
    },
    "audio": {
        "sources": [
            {
                "loc": [
                    4.66,
                    0.75,
                    1.5
                ],
                "audio": "LibriSpeech/train-clean-100/5789/57158/5789-57158-0016.flac",
                "gain": 1.0
            },
            {
                "loc": [
                    4.22,
                    5.91,
                    1.5
                ],
                "audio": "LibriSpeech/train-clean-100/5049/25947/5049-25947-0043.flac",
                "gain": 1.0
            },
            {
                "loc": [
                    1.33,
                    5.65,
                    1.5
                ],
                "audio": "LibriSpeech/train-clean-100/211/122425/211-122425-0077.flac",
                "gain": 1.0
            },
            {
                "loc": [
                    4.38,
                    2.49,
                    1.5
                ],
                "audio": "LibriSpeech/train-clean-100/5789/57195/5789-57195-0035.flac",
                "gain": 1.0
            },
            {
                "loc": [
                    3.03,
                    1.24,
                    0.52
                ],
                "audio": "wham_noise/tr/40bo030j_2.1197_20po010i_-2.1197.wav",
                "gain": 0.79
            }
        ],
        "duration": 10.0,
        "fs": 16000
    }
}